odoo/addons/product_logistics_uom_net_weight/README.rst
odoo/addons/product_logistics_uom_net_weight/__init__.py
odoo/addons/product_logistics_uom_net_weight/__manifest__.py
odoo/addons/product_logistics_uom_net_weight/hooks.py
odoo/addons/product_logistics_uom_net_weight/i18n/es.po
odoo/addons/product_logistics_uom_net_weight/i18n/it.po
odoo/addons/product_logistics_uom_net_weight/i18n/product_logistics_uom_net_weight.pot
odoo/addons/product_logistics_uom_net_weight/models/__init__.py
odoo/addons/product_logistics_uom_net_weight/models/product_product.py
odoo/addons/product_logistics_uom_net_weight/models/product_template.py
odoo/addons/product_logistics_uom_net_weight/readme/CONFIGURE.rst
odoo/addons/product_logistics_uom_net_weight/readme/CONTRIBUTORS.rst
odoo/addons/product_logistics_uom_net_weight/readme/DESCRIPTION.rst
odoo/addons/product_logistics_uom_net_weight/readme/INSTALL.rst
odoo/addons/product_logistics_uom_net_weight/readme/USAGE.rst
odoo/addons/product_logistics_uom_net_weight/static/description/icon.png
odoo/addons/product_logistics_uom_net_weight/static/description/index.html
odoo/addons/product_logistics_uom_net_weight/tests/__init__.py
odoo/addons/product_logistics_uom_net_weight/tests/test_product_logistics_uom_net_weight.py
odoo/addons/product_logistics_uom_net_weight/views/product_product.xml
odoo/addons/product_logistics_uom_net_weight/views/product_template.xml
odoo_addon_product_logistics_uom_net_weight-16.0.1.0.0.4.dist-info/METADATA
odoo_addon_product_logistics_uom_net_weight-16.0.1.0.0.4.dist-info/WHEEL
odoo_addon_product_logistics_uom_net_weight-16.0.1.0.0.4.dist-info/top_level.txt
odoo_addon_product_logistics_uom_net_weight-16.0.1.0.0.4.dist-info/RECORD
