Metadata-Version: 2.1
Name: odoo-addon-product_logistics_uom_net_weight
Version: 16.0.1.0.0.4
Summary: Integration module for product_logistics_uom and product_net_weight compatibility
Home-page: https://github.com/OCA/product-attribute
Author: Factor Libre, Odoo Community Association (OCA)
Author-email: support@odoo-community.org
License: AGPL-3
Classifier: Programming Language :: Python
Classifier: Framework :: Odoo
Classifier: Framework :: Odoo :: 16.0
Classifier: License :: OSI Approved :: GNU Affero General Public License v3
Classifier: Development Status :: 4 - Beta
Requires-Python: >=3.10
Requires-Dist: odoo-addon-product-logistics-uom<16.1dev,>=16.0dev
Requires-Dist: odoo-addon-product-net-weight<16.1dev,>=16.0dev
Requires-Dist: odoo<16.1dev,>=16.0a
